cropioai/__init__.py
cropioai/agent.py
cropioai/cropio.py
cropioai/llm.py
cropioai/process.py
cropioai/task.py
cropioai/agents/__init__.py
cropioai/agents/cropio_agent_executor.py
cropioai/agents/parser.py
cropioai/agents/tools_handler.py
cropioai/agents/agent_builder/__init__.py
cropioai/agents/agent_builder/base_agent.py
cropioai/agents/agent_builder/base_agent_executor_mixin.py
cropioai/agents/agent_builder/utilities/__init__.py
cropioai/agents/agent_builder/utilities/base_output_converter.py
cropioai/agents/agent_builder/utilities/base_token_process.py
cropioai/agents/cache/__init__.py
cropioai/agents/cache/cache_handler.py
cropioai/cli/__init__.py
cropioai/cli/add_cropio_to_flow.py
cropioai/cli/cli.py
cropioai/cli/command.py
cropioai/cli/config.py
cropioai/cli/constants.py
cropioai/cli/create_cropio.py
cropioai/cli/create_flow.py
cropioai/cli/cropio_chat.py
cropioai/cli/evaluate_cropio.py
cropioai/cli/git.py
cropioai/cli/ignite_flow.py
cropioai/cli/install_cropio.py
cropioai/cli/plot_flow.py
cropioai/cli/plus_api.py
cropioai/cli/provider.py
cropioai/cli/replay_from_task.py
cropioai/cli/reset_memories_command.py
cropioai/cli/run_cropio.py
cropioai/cli/takeoff_flow.py
cropioai/cli/train_cropio.py
cropioai/cli/update_cropio.py
cropioai/cli/utils.py
cropioai/cli/version.py
cropioai/cli/authentication/__init__.py
cropioai/cli/authentication/constants.py
cropioai/cli/authentication/main.py
cropioai/cli/authentication/token.py
cropioai/cli/authentication/utils.py
cropioai/cli/deploy/__init__.py
cropioai/cli/deploy/main.py
cropioai/cli/templates/__init__.py
cropioai/cli/templates/cropio/.gitignore
cropioai/cli/templates/cropio/README.md
cropioai/cli/templates/cropio/__init__.py
cropioai/cli/templates/cropio/cropio.py
cropioai/cli/templates/cropio/main.py
cropioai/cli/templates/cropio/pyproject.toml
cropioai/cli/templates/cropio/config/agents.yaml
cropioai/cli/templates/cropio/config/tasks.yaml
cropioai/cli/templates/cropio/knowledge/user_preference.txt
cropioai-0.4.0.dist-info/METADATA
cropioai-0.4.0.dist-info/WHEEL
cropioai-0.4.0.dist-info/entry_points.txt
cropioai-0.4.0.dist-info/licenses/LICENSE
cropioai-0.4.0.dist-info/RECORD
